smgantt/__init__.py
smgantt-0.0.5.dist-info/METADATA
smgantt-0.0.5.dist-info/WHEEL
smgantt-0.0.5.dist-info/entry_points.txt
smgantt-0.0.5.dist-info/top_level.txt
smgantt-0.0.5.dist-info/RECORD
