Metadata-Version: 2.1
Name: smgantt
Version: 0.0.5
Summary: Snakemake Gantt
Home-page: https://gitee.com/xhqsm/smgantt/
Author: singchen
Author-email: xhqsm@qq.com
License: MIT
Platform: UNKNOWN
Requires-Dist: kaleido
Requires-Dist: pandas
Requires-Dist: plotly
